van_classification_tensorflow/__init__.py
van_classification_tensorflow/version.json
van_classification_tensorflow/models/__init__.py
van_classification_tensorflow/models/config.py
van_classification_tensorflow/models/utils.py
van_classification_tensorflow/models/van.py
van_classification_tensorflow/models/layers/__init__.py
van_classification_tensorflow/models/layers/attention.py
van_classification_tensorflow/models/layers/block.py
van_classification_tensorflow/models/layers/dwconv.py
van_classification_tensorflow/models/layers/lka.py
van_classification_tensorflow/models/layers/mlp.py
van_classification_tensorflow/models/layers/overlap_patch_embed.py
van_classification_tensorflow/models/layers/utils.py
van_classification_tensorflow-1.0.3.dist-info/LICENSE
van_classification_tensorflow-1.0.3.dist-info/METADATA
van_classification_tensorflow-1.0.3.dist-info/WHEEL
van_classification_tensorflow-1.0.3.dist-info/top_level.txt
van_classification_tensorflow-1.0.3.dist-info/RECORD
