Metadata-Version: 2.1
Name: van-classification-tensorflow
Version: 1.0.3
Summary: TensorFlow 2.X reimplementation of Visual Attention Network, Meng-Hao Guo, Cheng-Ze Lu, Zheng-Ning Liu, Ming-Ming Cheng, Shi-Min Hu.
Home-page: https://github.com/EMalagoli92/VAN-Classification-TensorFlow
Author: EMalagoli92
Author-email: emala.892@gmail.com
License: MIT
Classifier: Development Status :: 5 - Production/Stable
Classifier: Intended Audience :: Developers
Classifier: Intended Audience :: Education
Classifier: Intended Audience :: Science/Research
Classifier: License :: OSI Approved :: MIT License
Classifier: Programming Language :: Python :: 3
Classifier: Topic :: Scientific/Engineering
Classifier: Topic :: Software Development
Classifier: Topic :: Software Development :: Libraries
Classifier: Topic :: Software Development :: Libraries :: Python Modules
Requires-Python: >=3.9
License-File: LICENSE
Requires-Dist: absl-py (==1.4.0)
Requires-Dist: astunparse (==1.6.3)
Requires-Dist: cachetools (==5.3.0)
Requires-Dist: certifi (==2022.12.7)
Requires-Dist: charset-normalizer (==3.0.1)
Requires-Dist: cloudpickle (==2.2.1)
Requires-Dist: decorator (==5.1.1)
Requires-Dist: dm-tree (==0.1.8)
Requires-Dist: flatbuffers (==1.12)
Requires-Dist: gast (==0.4.0)
Requires-Dist: google-auth (==2.16.2)
Requires-Dist: google-auth-oauthlib (==0.4.6)
Requires-Dist: google-pasta (==0.2.0)
Requires-Dist: grpcio (==1.51.3)
Requires-Dist: h5py (==3.8.0)
Requires-Dist: idna (==3.4)
Requires-Dist: importlib-metadata (==6.0.0)
Requires-Dist: keras (==2.9.0)
Requires-Dist: Keras-Preprocessing (==1.1.2)
Requires-Dist: libclang (==15.0.6.1)
Requires-Dist: Markdown (==3.4.1)
Requires-Dist: MarkupSafe (==2.1.2)
Requires-Dist: numpy (==1.24.2)
Requires-Dist: oauthlib (==3.2.2)
Requires-Dist: opt-einsum (==3.3.0)
Requires-Dist: packaging (==23.0)
Requires-Dist: protobuf (==3.19.6)
Requires-Dist: pyasn1 (==0.4.8)
Requires-Dist: pyasn1-modules (==0.2.8)
Requires-Dist: requests (==2.28.2)
Requires-Dist: requests-oauthlib (==1.3.1)
Requires-Dist: rsa (==4.9)
Requires-Dist: six (==1.16.0)
Requires-Dist: tensorboard (==2.9.1)
Requires-Dist: tensorboard-data-server (==0.6.1)
Requires-Dist: tensorboard-plugin-wit (==1.8.1)
Requires-Dist: tensorflow (==2.9.0)
Requires-Dist: tensorflow-addons (==0.17.1)
Requires-Dist: tensorflow-estimator (==2.9.0)
Requires-Dist: tensorflow-io-gcs-filesystem (==0.31.0)
Requires-Dist: tensorflow-probability (==0.17.0)
Requires-Dist: termcolor (==2.2.0)
Requires-Dist: typeguard (==2.13.3)
Requires-Dist: typing-extensions (==4.5.0)
Requires-Dist: urllib3 (==1.26.14)
Requires-Dist: Werkzeug (==2.2.3)
Requires-Dist: wrapt (==1.15.0)
Requires-Dist: zipp (==3.15.0)
